synapse_auto_compressor-0.1.4.dist-info/METADATA
synapse_auto_compressor-0.1.4.dist-info/WHEEL
synapse_auto_compressor/__init__.py
synapse_auto_compressor/ffi.py
synapse_auto_compressor/synapse_auto_compressor.so
synapse_auto_compressor-0.1.4.dist-info/RECORD
