Metadata-Version: 2.3
Name: synapse_auto_compressor
Version: 0.1.4
Author: William Ashton
Requires-Python: >=3.7
Project-URL: Source, https://github.com/matrix-org/rust-synapse-compress-state
